million_verifier/__init__.py
million_verifier/_client.py
million_verifier/_client_core.py
million_verifier/_enums.py
million_verifier/_exceptions.py
million_verifier/_formats.py
million_verifier/_utils.py
million_verifier_client-0.1.2.dist-info/LICENSE
million_verifier_client-0.1.2.dist-info/METADATA
million_verifier_client-0.1.2.dist-info/WHEEL
million_verifier_client-0.1.2.dist-info/RECORD
