Metadata-Version: 2.1
Name: million-verifier-client
Version: 0.1.2
Summary: 
Author: mattjohnrock
Author-email: johnstone.mattjames@gmail.com
Requires-Python: >=3.10,<3.12
Classifier: Programming Language :: Python :: 3
Classifier: Programming Language :: Python :: 3.10
Classifier: Programming Language :: Python :: 3.11
Requires-Dist: requests (>=2.31.0,<3.0.0)
